unolet/__init__.py
unolet/api.py
unolet/config.py
unolet/exceptions.py
unolet/fields.py
unolet/models.py
unolet/utils.py
unolet/assets/README.md
unolet/erp/__init__.py
unolet/services/__init__.py
unolet-0.0.2.dist-info/LICENSE
unolet-0.0.2.dist-info/METADATA
unolet-0.0.2.dist-info/WHEEL
unolet-0.0.2.dist-info/top_level.txt
unolet-0.0.2.dist-info/RECORD
