Metadata-Version: 2.1
Name: unolet
Version: 0.0.2
Summary: Python library to connect with Unolet API
Author-email: Unolet <info@unolet.com>, Wilmer Martinez <info@wilmermartinez.dev>
License: MIT License
Project-URL: Homepage, https://github.com/wilmerm/unolet-python-api
Project-URL: Issues, https://github.com/wilmerm/unolet-python-api/issues
Project-URL: Repository, https://github.com/wilmerm/unolet-python-api
Keywords: unolet,api,erp,enterprise resource planning,business management,accounting,inventory,sales,purchases,quotations,invoices,warehouse management,python client,rest api,django,data integration,automation,business solutions,python library
Classifier: Development Status :: 3 - Alpha
Classifier: Intended Audience :: Developers
Classifier: Topic :: Software Development :: Libraries :: Python Modules
Classifier: Environment :: Web Environment
Classifier: License :: OSI Approved :: MIT License
Classifier: Natural Language :: English
Classifier: Natural Language :: Spanish
Classifier: Programming Language :: Python
Classifier: Programming Language :: Python :: 3
Classifier: Programming Language :: Python :: 3 :: Only
Classifier: Programming Language :: Python :: 3.0
Classifier: Programming Language :: Python :: 3.1
Classifier: Programming Language :: Python :: 3.2
Classifier: Programming Language :: Python :: 3.3
Classifier: Programming Language :: Python :: 3.4
Classifier: Programming Language :: Python :: 3.5
Classifier: Programming Language :: Python :: 3.6
Classifier: Programming Language :: Python :: 3.7
Classifier: Programming Language :: Python :: 3.8
Classifier: Programming Language :: Python :: 3.9
Classifier: Programming Language :: Python :: 3.10
Classifier: Programming Language :: Python :: 3.11
Classifier: Programming Language :: Python :: 3.12
Classifier: Programming Language :: Python :: 3.13
Requires-Python: >=3.8
License-File: LICENSE
Requires-Dist: requests
Requires-Dist: python-dateutil
